RL_for_reco/AutoEncoder.py
RL_for_reco/Item_Reco.py
RL_for_reco/Network_for_Reco.py
RL_for_reco/RL_Learn.py
RL_for_reco/TorchModel.py
RL_for_reco/__init__.py
RL_for_reco/class_balanced_loss.py
RL_for_reco/rank_gauss.py
RL_for_reco-1.0.27.dist-info/LICENSE
RL_for_reco-1.0.27.dist-info/METADATA
RL_for_reco-1.0.27.dist-info/WHEEL
RL_for_reco-1.0.27.dist-info/top_level.txt
RL_for_reco-1.0.27.dist-info/RECORD
