Metadata-Version: 2.1
Name: RL-for-reco
Version: 1.0.27
Summary: A Python toolkit of Deep Reinforcement Learning for Structured Data-Oriented Recommendation.
Home-page: https://github.com/gowun/RL_for_reco.git
Author: Gowun Jeong
Author-email: gowun.jeong@gmail.com
License: MIT
Platform: UNKNOWN
Classifier: Programming Language :: Python :: 3
Classifier: License :: OSI Approved :: MIT License
Classifier: Operating System :: OS Independent
Requires-Python: >=3.6
Requires-Dist: torch (>=1.4.0)
Requires-Dist: torchvision (>=0.5.0)
Requires-Dist: scikit-learn (>=0.22.2.post1)
Requires-Dist: scipy (>=1.4.1)
Requires-Dist: matplotlib (>=3.2.1)
Requires-Dist: mushroom-rl (>=1.4.0)
